Metadata-Version: 2.1
Name: django-mazer
Version: 0.0.1
Summary: Django Template Mazer
Home-page: https://github.com/ElebrUS/DjangoMazer
Author: Nikita Marchenko
Author-email: megaelebrus@gmail.com
License: UNKNOWN
Platform: UNKNOWN
Classifier: Programming Language :: Python :: 3.9
Classifier: License :: OSI Approved :: MIT License
Classifier: Operating System :: OS Independent
Requires-Python: >=3.6
License-File: LICENSE
